dash_gauge/Dash7SegmentDisplay.py
dash_gauge/DashGauge.py
dash_gauge/DashRCJoystick.py
dash_gauge/DashRotaryKnob.py
dash_gauge/DashThermostat.py
dash_gauge/__init__.py
dash_gauge/_imports_.py
dash_gauge/dash_gauge.min.js
dash_gauge/dash_gauge.min.js.map
dash_gauge/metadata.json
dash_gauge/package-info.json
dash_gauge-0.0.2.dist-info/LICENSE
dash_gauge-0.0.2.dist-info/METADATA
dash_gauge-0.0.2.dist-info/WHEEL
dash_gauge-0.0.2.dist-info/top_level.txt
dash_gauge-0.0.2.dist-info/RECORD
