Metadata-Version: 2.2
Name: dash_gauge
Version: 0.0.2
Summary: Fancy gauge and knob components for Dash applications
Author: Pip Install Python <pipinstallpython@gmail.com>
License: MIT
Classifier: Framework :: Dash
License-File: LICENSE
Dynamic: author
Dynamic: classifier
Dynamic: description
Dynamic: description-content-type
Dynamic: license
Dynamic: summary
